time_mcp_pypi-1.0.6.dist-info/licenses/LICENSE
time_mcp_server/__init__.py
time_mcp_server/main.py
time_mcp_pypi-1.0.6.dist-info/METADATA
time_mcp_pypi-1.0.6.dist-info/WHEEL
time_mcp_pypi-1.0.6.dist-info/entry_points.txt
time_mcp_pypi-1.0.6.dist-info/top_level.txt
time_mcp_pypi-1.0.6.dist-info/RECORD
