Metadata-Version: 2.4
Name: time-mcp-pypi
Version: 1.0.6
Summary: A Model Context Protocol (MCP) server that provides current UTC time in RFC 3339 format
License-Expression: MIT
Project-URL: Homepage, https://github.com/domdomegg/time-mcp-pypi
Project-URL: Repository, https://github.com/domdomegg/time-mcp-pypi.git
Project-URL: Issues, https://github.com/domdomegg/time-mcp-pypi/issues
Keywords: mcp,model-context-protocol,time,utc,timestamp,mcp-name:io.github.domdomegg/time-mcp-pypi
Classifier: Development Status :: 4 - Beta
Classifier: Intended Audience :: Developers
Classifier: Programming Language :: Python :: 3
Classifier: Programming Language :: Python :: 3.8
Classifier: Programming Language :: Python :: 3.9
Classifier: Programming Language :: Python :: 3.10
Classifier: Programming Language :: Python :: 3.11
Classifier: Programming Language :: Python :: 3.12
Classifier: Topic :: Software Development :: Libraries :: Python Modules
Requires-Python: >=3.8
License-File: LICENSE
Requires-Dist: mcp==1.13.1
Dynamic: license-file
